GoYuyanGaojiBianchengFix1/README.md
GoYuyanGaojiBianchengFix1/__init__.py
GoYuyanGaojiBianchengFix1/__main__.py
GoYuyanGaojiBianchengFix1/file.epub
GoYuyanGaojiBianchengFix1/index.html
GoYuyanGaojiBianchengFix1/css/__init__.py
GoYuyanGaojiBianchengFix1/css/annotations.css
GoYuyanGaojiBianchengFix1/css/main.css
GoYuyanGaojiBianchengFix1/css/normalize.css
GoYuyanGaojiBianchengFix1/css/popup.css
GoYuyanGaojiBianchengFix1/font/__init__.py
GoYuyanGaojiBianchengFix1/font/fontello.eot
GoYuyanGaojiBianchengFix1/font/fontello.svg
GoYuyanGaojiBianchengFix1/font/fontello.ttf
GoYuyanGaojiBianchengFix1/font/fontello.woff
GoYuyanGaojiBianchengFix1/img/__init__.py
GoYuyanGaojiBianchengFix1/img/annotator-glyph-sprite.png
GoYuyanGaojiBianchengFix1/img/annotator-icon-sprite.png
GoYuyanGaojiBianchengFix1/img/apple-touch-icon.png
GoYuyanGaojiBianchengFix1/img/cancelfullscreen.png
GoYuyanGaojiBianchengFix1/img/close.png
GoYuyanGaojiBianchengFix1/img/fullscreen.png
GoYuyanGaojiBianchengFix1/img/loader.gif
GoYuyanGaojiBianchengFix1/img/menu-icon.png
GoYuyanGaojiBianchengFix1/img/save.png
GoYuyanGaojiBianchengFix1/img/saved.png
GoYuyanGaojiBianchengFix1/img/settings-s.png
GoYuyanGaojiBianchengFix1/img/settings.png
GoYuyanGaojiBianchengFix1/img/star.png
GoYuyanGaojiBianchengFix1/js/__init__.py
GoYuyanGaojiBianchengFix1/js/epub.js
GoYuyanGaojiBianchengFix1/js/epub.min.js
GoYuyanGaojiBianchengFix1/js/epub.min.map
GoYuyanGaojiBianchengFix1/js/hooks.min.js
GoYuyanGaojiBianchengFix1/js/hooks.min.map
GoYuyanGaojiBianchengFix1/js/reader.js
GoYuyanGaojiBianchengFix1/js/reader.js.map
GoYuyanGaojiBianchengFix1/js/reader.min.js
GoYuyanGaojiBianchengFix1/js/reader.min.map
GoYuyanGaojiBianchengFix1/js/hooks/__init__.py
GoYuyanGaojiBianchengFix1/js/hooks/extensions/__init__.py
GoYuyanGaojiBianchengFix1/js/hooks/extensions/highlight.js
GoYuyanGaojiBianchengFix1/js/libs/__init__.py
GoYuyanGaojiBianchengFix1/js/libs/jquery.min.js
GoYuyanGaojiBianchengFix1/js/libs/localforage.min.js
go_yuyan_gaoji_biancheng_fix1-2025.3.24.0.dist-info/METADATA
go_yuyan_gaoji_biancheng_fix1-2025.3.24.0.dist-info/WHEEL
go_yuyan_gaoji_biancheng_fix1-2025.3.24.0.dist-info/entry_points.txt
go_yuyan_gaoji_biancheng_fix1-2025.3.24.0.dist-info/top_level.txt
go_yuyan_gaoji_biancheng_fix1-2025.3.24.0.dist-info/RECORD
